MANIFEST.in
README.md
README.rst
setup.py
bin/fast-lineage-caller
fast_lineage_caller/__init__.py
fast_lineage_caller/lineage_caller_fasta.py
fast_lineage_caller/lineage_caller_vcf.py
fast_lineage_caller/snp_scheme_parser.py
fast_lineage_caller/utils.py
fast_lineage_caller.egg-info/PKG-INFO
fast_lineage_caller.egg-info/SOURCES.txt
fast_lineage_caller.egg-info/dependency_links.txt
fast_lineage_caller.egg-info/not-zip-safe
fast_lineage_caller.egg-info/top_level.txt
snp_schemes/__init__.py
snp_schemes/coll.tsv
snp_schemes/freschi.tsv
snp_schemes/lipworth.tsv
snp_schemes/shitikov.tsv
snp_schemes/snp_scheme_format.md
snp_schemes/stucki.tsv